README.md
setup.py
odoo_connector/__init__.py
odoo_connector/connectors.py
odoo_connector/protocols.py
odoo_connector.egg-info/PKG-INFO
odoo_connector.egg-info/SOURCES.txt
odoo_connector.egg-info/dependency_links.txt
odoo_connector.egg-info/top_level.txt