Metadata-Version: 2.1
Name: odoo-connector
Version: 1.0.3
Summary: This is a library that allow an easy and friendly connection with an Odoo ERP instance on Pyhton 2.x
Home-page: https://github.com/franklintiel/odoo-connector/wiki
Author: Franklin Sarmiento
Author-email: franklinitiel@gmail.com
License: MIT
Project-URL: Source, https://github.com/franklintiel/odoo-connector
Project-URL: Documentation, https://github.com/franklintiel/odoo-connector/
Project-URL: Tracker, https://github.com/franklintiel/odoo-connector/issues
Keywords: odoo connector connect interface connection odoo_connection odoo_connect odoo_connector odoo_interface odoo_protocol
Platform: UNKNOWN
Classifier: Development Status :: 5 - Production/Stable
Classifier: License :: OSI Approved :: MIT License
Classifier: Programming Language :: Python :: 2.7
Requires-Python: >=2.*
